pyogrio/errors.py
pyogrio/core.py
pyogrio/_version.py
pyogrio/raw.py
pyogrio/_err.cpython-313-x86_64-linux-gnu.so
pyogrio/_ogr.cpython-313-x86_64-linux-gnu.so
pyogrio/_io.cpython-313-x86_64-linux-gnu.so
pyogrio/_env.py
pyogrio/_compat.py
pyogrio/util.py
pyogrio/_geometry.cpython-313-x86_64-linux-gnu.so
pyogrio/_vsi.cpython-313-x86_64-linux-gnu.so
pyogrio/__init__.py
pyogrio/geopandas.py
pyogrio/gdal_data/GDALConfig.cmake
pyogrio/gdal_data/inspire_cp_CadastralBoundary.gfs
pyogrio/gdal_data/grib2_table_4_2_0_17.csv
pyogrio/gdal_data/jpfgdgml_Cntr.gfs
pyogrio/gdal_data/GDALLogoBW.svg
pyogrio/gdal_data/grib2_center.csv
pyogrio/gdal_data/grib2_table_versions.csv
pyogrio/gdal_data/grib2_table_4_2_0_15.csv
pyogrio/gdal_data/s57attributes.csv
pyogrio/gdal_data/grib2_table_4_2_20_0.csv
pyogrio/gdal_data/jpfgdgml_AdmPt.gfs
pyogrio/gdal_data/grib2_table_4_2_local_MRMS.csv
pyogrio/gdal_data/jpfgdgml_RailCL.gfs
pyogrio/gdal_data/trailer.dxf
pyogrio/gdal_data/pdfcomposition.xsd
pyogrio/gdal_data/grib2_table_4_2_10_2.csv
pyogrio/gdal_data/grib2_table_4_2_4_2.csv
pyogrio/gdal_data/jpfgdgml_WStrA.gfs
pyogrio/gdal_data/GDALLogoColor.svg
pyogrio/gdal_data/grib2_table_4_2_3_3.csv
pyogrio/gdal_data/GDALLogoGS.svg
pyogrio/gdal_data/grib2_table_4_2_2_6.csv
pyogrio/gdal_data/jpfgdgml_LeveeEdge.gfs
pyogrio/gdal_data/ruian_vf_st_uvoh_v1.gfs
pyogrio/gdal_data/vicar.json
pyogrio/gdal_data/cubewerx_extra.wkt
pyogrio/gdal_data/grib2_table_4_2_3_4.csv
pyogrio/gdal_data/jpfgdgml_CommPt.gfs
pyogrio/gdal_data/GDAL-targets.cmake
pyogrio/gdal_data/grib2_table_4_2_0_21.csv
pyogrio/gdal_data/LICENSE.TXT
pyogrio/gdal_data/pci_ellips.txt
pyogrio/gdal_data/header.dxf
pyogrio/gdal_data/grib2_table_4_2_4_7.csv
pyogrio/gdal_data/eedaconf.json
pyogrio/gdal_data/s57objectclasses.csv
pyogrio/gdal_data/grib2_table_4_2_2_3.csv
pyogrio/gdal_data/grib2_table_4_2_1_1.csv
pyogrio/gdal_data/tms_NZTM2000.json
pyogrio/gdal_data/inspire_cp_BasicPropertyUnit.gfs
pyogrio-0.10.0.dist-info/LICENSE
pyogrio-0.10.0.dist-info/METADATA
pyogrio-0.10.0.dist-info/RECORD
pyogrio-0.10.0.dist-info/WHEEL
pyogrio-0.10.0.dist-info/top_level.txt
