Metadata-Version: 2.1
Name: pyogrio
Version: 0.10.0
Summary: Vectorized spatial vector file format I/O using GDAL/OGR
Author: pyogrio contributors
Author-email: "Brendan C. Ward" <bcward@astutespruce.com>
Maintainer: pyogrio contributors
License: MIT License
Project-URL: Home, https://pyogrio.readthedocs.io/
Project-URL: Repository, https://github.com/geopandas/pyogrio
Classifier: Development Status :: 5 - Production/Stable
Classifier: Intended Audience :: Science/Research
Classifier: License :: OSI Approved :: MIT License
Classifier: Operating System :: OS Independent
Classifier: Programming Language :: Python :: 3
Classifier: Topic :: Scientific/Engineering :: GIS
Requires-Python: >=3.9
License-File: LICENSE
Requires-Dist: certifi
Requires-Dist: numpy
Requires-Dist: packaging
Provides-Extra: dev
Requires-Dist: cython; extra == "dev"
Provides-Extra: test
Requires-Dist: pytest; extra == "test"
Requires-Dist: pytest-cov; extra == "test"
Provides-Extra: benchmark
Requires-Dist: pytest-benchmark; extra == "benchmark"
Provides-Extra: geopandas
Requires-Dist: geopandas; extra == "geopandas"
